{"directed": true, "multigraph": false, "graph": {}, "nodes": [{"lat": 400.0, "lon": 200.0, "id": "sourcebus"}, {"lat": 350.0, "lon": 200.0, "id": "650"}, {"lat": 300.0, "lon": 200.0, "id": "rg60"}, {"lat": 250.0, "lon": 200.0, "id": "632"}, {"lat": 200.0, "lon": 200.0, "id": "670"}, {"lat": 250.0, "lon": 350.0, "id": "633"}, {"lat": 250.0, "lon": 100.0, "id": "645"}, {"lat": 100.0, "lon": 200.0, "id": "671"}, {"lat": 250.0, "lon": 400.0, "id": "634"}, {"lat": 250.0, "lon": 0.0, "id": "646"}, {"lat": 0.0, "lon": 200.0, "id": "680"}, {"lat": 100.0, "lon": 100.0, "id": "684"}, {"lat": 100.0, "lon": 250.0, "id": "692"}, {"lat": 100.0, "lon": 0.0, "id": "611"}, {"lat": 0.0, "lon": 100.0, "id": "652"}, {"lat": 100.0, "lon": 400.0, "id": "675"}], "links": [{"source": "sourcebus", "target": "650"}, {"source": "650", "target": "rg60"}, {"source": "rg60", "target": "632"}, {"source": "632", "target": "670"}, {"source": "632", "target": "633"}, {"source": "632", "target": "645"}, {"source": "670", "target": "671"}, {"source": "633", "target": "634"}, {"source": "645", "target": "646"}, {"source": "671", "target": "680"}, {"source": "671", "target": "684"}, {"source": "671", "target": "692"}, {"source": "684", "target": "611"}, {"source": "684", "target": "652"}, {"source": "692", "target": "675"}]}